[
  {
    "full_name": "30-seconds/30-seconds-of-code",
    "stargazers_count": 89445,
    "open_issues_count": 6,
    "forks_count": 9527
  },
  {
    "full_name": "felipefialho/frontend-challenges",
    "stargazers_count": 7252,
    "open_issues_count": 0,
    "forks_count": 843
  },
  {
    "full_name": "30-seconds/30-seconds-of-css",
    "stargazers_count": 14958,
    "open_issues_count": 2,
    "forks_count": 1008
  },
  {
    "full_name": "thedaviddias/Front-End-Design-Checklist",
    "stargazers_count": 4140,
    "open_issues_count": 0,
    "forks_count": 325
  },
  {
    "full_name": "thedaviddias/Front-End-Performance-Checklist",
    "stargazers_count": 13836,
    "open_issues_count": 11,
    "forks_count": 1004
  },
  {
    "full_name": "responsively-org/responsively-app",
    "stargazers_count": 14459,
    "open_issues_count": 107,
    "forks_count": 623
  },
  {
    "full_name": "getify/You-Dont-Know-JS",
    "stargazers_count": 147683,
    "open_issues_count": 130,
    "forks_count": 29365
  },
  {
    "full_name": "thedaviddias/Front-End-Checklist",
    "stargazers_count": 57424,
    "open_issues_count": 8,
    "forks_count": 5585
  },
  {
    "full_name": "Ajaykumarrachuri/starter",
    "stargazers_count": 2,
    "open_issues_count": 0,
    "forks_count": 0
  },
  {
    "full_name": "antoine92190/vue-advanced-chat",
    "stargazers_count": 675,
    "open_issues_count": 10,
    "forks_count": 209
  },
  {
    "full_name": "kamranahmedse/developer-roadmap",
    "stargazers_count": 181387,
    "open_issues_count": 89,
    "forks_count": 26052
  },
  {
    "full_name": "zhiwehu/Python-programming-exercises",
    "stargazers_count": 17933,
    "open_issues_count": 140,
    "forks_count": 6023
  },
  {
    "full_name": "practical-tutorials/project-based-learning",
    "stargazers_count": 60335,
    "open_issues_count": 28,
    "forks_count": 9246
  }
]